odoo/addons/l10n_it_account_balance_report/README.rst
odoo/addons/l10n_it_account_balance_report/__init__.py
odoo/addons/l10n_it_account_balance_report/__manifest__.py
odoo/addons/l10n_it_account_balance_report/data/account_type.xml
odoo/addons/l10n_it_account_balance_report/i18n/it.po
odoo/addons/l10n_it_account_balance_report/i18n/l10n_it_account_balance_report.pot
odoo/addons/l10n_it_account_balance_report/migrations/12.0.1.0.5/post-migrate.py
odoo/addons/l10n_it_account_balance_report/models/__init__.py
odoo/addons/l10n_it_account_balance_report/models/account_account.py
odoo/addons/l10n_it_account_balance_report/models/account_type.py
odoo/addons/l10n_it_account_balance_report/readme/CONTRIBUTORS.rst
odoo/addons/l10n_it_account_balance_report/readme/CREDITS.rst
odoo/addons/l10n_it_account_balance_report/readme/DESCRIPTION.rst
odoo/addons/l10n_it_account_balance_report/readme/USAGE.rst
odoo/addons/l10n_it_account_balance_report/report/__init__.py
odoo/addons/l10n_it_account_balance_report/report/account_balance_report.py
odoo/addons/l10n_it_account_balance_report/report/account_balance_report_xlsx.py
odoo/addons/l10n_it_account_balance_report/report/reports.xml
odoo/addons/l10n_it_account_balance_report/report/trial_balance_report.py
odoo/addons/l10n_it_account_balance_report/report/templates/account_balance_report.xml
odoo/addons/l10n_it_account_balance_report/static/description/icon.png
odoo/addons/l10n_it_account_balance_report/static/description/index.html
odoo/addons/l10n_it_account_balance_report/tests/__init__.py
odoo/addons/l10n_it_account_balance_report/tests/test_balance_report.py
odoo/addons/l10n_it_account_balance_report/views/account_types.xml
odoo/addons/l10n_it_account_balance_report/views/action_client.xml
odoo/addons/l10n_it_account_balance_report/wizard/__init__.py
odoo/addons/l10n_it_account_balance_report/wizard/wizard_account_balance_report.py
odoo/addons/l10n_it_account_balance_report/wizard/wizard_account_balance_report.xml
odoo12_addon_l10n_it_account_balance_report-12.0.1.1.0.dist-info/METADATA
odoo12_addon_l10n_it_account_balance_report-12.0.1.1.0.dist-info/WHEEL
odoo12_addon_l10n_it_account_balance_report-12.0.1.1.0.dist-info/top_level.txt
odoo12_addon_l10n_it_account_balance_report-12.0.1.1.0.dist-info/RECORD
