Metadata-Version: 2.1
Name: odoo12-addon-l10n-it-account-balance-report
Version: 12.0.1.1.0
Summary: Rendicontazione .pdf e .xls per stato patrimoniale e conto economico a sezioni contrapposte
Home-page: https://github.com/OCA/l10n-italy/tree/12.0/l10n_it_account_balance_report
Author: Odoo Community Association (OCA), Openforce
Author-email: support@odoo-community.org
License: AGPL-3
Platform: UNKNOWN
Classifier: Programming Language :: Python
Classifier: Framework :: Odoo
Classifier: Framework :: Odoo :: 12.0
Classifier: License :: OSI Approved :: GNU Affero General Public License v3
Requires-Python: >=3.5
Requires-Dist: odoo12-addon-account-financial-report
Requires-Dist: odoo12-addon-account-type-menu
Requires-Dist: odoo12-addon-l10n-it-account
Requires-Dist: odoo (<12.1dev,>=12.0a)
